[
  {
    "Id": 1,
    "Nome": "Simone",
    "ImmagineId": 1,
    "Stelle": 4.0,
    "Data": "2024-03-21T00:00:00",
    "Commento": "belin che bella",
    "Visibile": true,
    "Moderato": true
  },
  {
    "Id": 2,
    "Nome": "dsfbslbglskjg",
    "ImmagineId": 1,
    "Stelle": 4.0,
    "Data": "2024-03-21T00:00:00+01:00",
    "Commento": "sfdgdagegr",
    "Visibile": true,
    "Moderato": false
  },
  {
    "Id": 3,
    "Nome": "fggdgf",
    "ImmagineId": 4,
    "Stelle": 2.0,
    "Data": "2024-03-21T00:00:00+01:00",
    "Commento": "gdgdfsdfd",
    "Visibile": true,
    "Moderato": false
  },
  {
    "Id": 4,
    "Nome": "idshflsbakf",
    "ImmagineId": 1,
    "Stelle": 5.0,
    "Data": "2024-03-22T00:00:00+01:00",
    "Commento": "lsbdvuilbvakfbkhkab",
    "Visibile": false,
    "Moderato": true
  },
  {
    "Id": 5,
    "Nome": "carlo",
    "ImmagineId": 1,
    "Stelle": 1.0,
    "Data": "2024-03-22T00:00:00+01:00",
    "Commento": "buco del culo",
    "Visibile": false,
    "Moderato": true
  },
  {
    "Id": 6,
    "Nome": "alex",
    "ImmagineId": 1,
    "Stelle": 5.0,
    "Data": "2024-03-22T00:00:00+01:00",
    "Commento": "w la figaaaaaaaaaaa",
    "Visibile": false,
    "Moderato": true
  },
  {
    "Id": 7,
    "Nome": "fabietto",
    "ImmagineId": 5,
    "Stelle": 4.0,
    "Data": "2024-03-22T00:00:00+01:00",
    "Commento": "bell'albero",
    "Visibile": true,
    "Moderato": false
  },
  {
    "Id": 8,
    "Nome": "dylan",
    "ImmagineId": 12,
    "Stelle": 2.0,
    "Data": "2024-03-22T00:00:00+01:00",
    "Commento": "djkpsghzkgbsrdfnsdfbsdobfsobfafa fsugfsuoagfosa fioagfoisagf soufg sofgso fsaoufg sof sofg soufg soaufg suofg sofgsofg saofgs fosa ",
    "Visibile": true,
    "Moderato": false
  },
  {
    "Id": 9,
    "Nome": "aidaffafda",
    "ImmagineId": 1,
    "Stelle": 3.0,
    "Data": "2024-03-22T00:00:00+01:00",
    "Commento": "sjinfisfnfds",
    "Visibile": true,
    "Moderato": false
  },
  {
    "Id": 10,
    "Nome": "eew",
    "ImmagineId": 12,
    "Stelle": 2.0,
    "Data": "2024-03-22T00:00:00+01:00",
    "Commento": "efwefwe",
    "Visibile": true,
    "Moderato": false
  },
  {
    "Id": 11,
    "Nome": "retretre",
    "ImmagineId": 10,
    "Stelle": 1.0,
    "Data": "2024-03-22T00:00:00+01:00",
    "Commento": "erterte",
    "Visibile": true,
    "Moderato": false
  },
  {
    "Id": 12,
    "Nome": "Emanuela ",
    "ImmagineId": 64,
    "Stelle": 5.0,
    "Data": "2024-03-24T00:00:00+01:00",
    "Commento": null,
    "Visibile": true,
    "Moderato": false
  },
  {
    "Id": 13,
    "Nome": "simo",
    "ImmagineId": 8,
    "Stelle": 5.0,
    "Data": "2024-03-24T00:00:00+01:00",
    "Commento": "bella bella",
    "Visibile": true,
    "Moderato": true
  },
  {
    "Id": 14,
    "Nome": "simo",
    "ImmagineId": 9,
    "Stelle": 5.0,
    "Data": "2024-03-24T00:00:00+01:00",
    "Commento": "sndbasbdalsba",
    "Visibile": true,
    "Moderato": false
  },
  {
    "Id": 15,
    "Nome": "cscsa",
    "ImmagineId": 50,
    "Stelle": 5.0,
    "Data": "2024-03-24T00:00:00+01:00",
    "Commento": "<xzxz<",
    "Visibile": true,
    "Moderato": false
  },
  {
    "Id": 16,
    "Nome": "x<x<x<",
    "ImmagineId": 50,
    "Stelle": 5.0,
    "Data": "2024-03-24T00:00:00+01:00",
    "Commento": "axz<xz<",
    "Visibile": true,
    "Moderato": true
  },
  {
    "Id": 17,
    "Nome": "wewew",
    "ImmagineId": 12,
    "Stelle": 3.0,
    "Data": "2024-03-24T00:00:00+01:00",
    "Commento": "cdcdscd",
    "Visibile": true,
    "Moderato": false
  },
  {
    "Id": 18,
    "Nome": "wewew",
    "ImmagineId": 12,
    "Stelle": 3.0,
    "Data": "2024-03-24T00:00:00+01:00",
    "Commento": "cdcdscd",
    "Visibile": true,
    "Moderato": false
  },
  {
    "Id": 19,
    "Nome": "wewew",
    "ImmagineId": 12,
    "Stelle": 3.0,
    "Data": "2024-03-24T00:00:00+01:00",
    "Commento": "cdcdscd",
    "Visibile": true,
    "Moderato": false
  },
  {
    "Id": 20,
    "Nome": "wewew",
    "ImmagineId": 12,
    "Stelle": 3.0,
    "Data": "2024-03-24T00:00:00+01:00",
    "Commento": "cdcdscd",
    "Visibile": true,
    "Moderato": false
  },
  {
    "Id": 21,
    "Nome": "wewew",
    "ImmagineId": 12,
    "Stelle": 3.0,
    "Data": "2024-03-24T00:00:00+01:00",
    "Commento": "cdcdscd",
    "Visibile": true,
    "Moderato": false
  },
  {
    "Id": 22,
    "Nome": "wewew",
    "ImmagineId": 12,
    "Stelle": 3.0,
    "Data": "2024-03-24T00:00:00+01:00",
    "Commento": "cdcdscd",
    "Visibile": true,
    "Moderato": false
  },
  {
    "Id": 23,
    "Nome": "wewew",
    "ImmagineId": 12,
    "Stelle": 3.0,
    "Data": "2024-03-24T00:00:00+01:00",
    "Commento": "cdcdscd",
    "Visibile": true,
    "Moderato": false
  },
  {
    "Id": 24,
    "Nome": "wewew",
    "ImmagineId": 12,
    "Stelle": 3.0,
    "Data": "2024-03-24T00:00:00+01:00",
    "Commento": "cdcdscd",
    "Visibile": false,
    "Moderato": true
  },
  {
    "Id": 25,
    "Nome": "wewew",
    "ImmagineId": 12,
    "Stelle": 3.0,
    "Data": "2024-03-24T00:00:00+01:00",
    "Commento": "cdcdscd",
    "Visibile": true,
    "Moderato": false
  },
  {
    "Id": 26,
    "Nome": "wewew",
    "ImmagineId": 12,
    "Stelle": 3.0,
    "Data": "2024-03-24T00:00:00+01:00",
    "Commento": "cdcdscd",
    "Visibile": true,
    "Moderato": false
  },
  {
    "Id": 27,
    "Nome": "xcscsac",
    "ImmagineId": 3,
    "Stelle": 5.0,
    "Data": "2024-03-24T00:00:00+01:00",
    "Commento": "zcxzcszczs",
    "Visibile": true,
    "Moderato": false
  },
  {
    "Id": 28,
    "Nome": "ccscsa",
    "ImmagineId": 62,
    "Stelle": 1.0,
    "Data": "2024-03-24T00:00:00+01:00",
    "Commento": "csdsdas",
    "Visibile": true,
    "Moderato": false
  },
  {
    "Id": 29,
    "Nome": "vfgreger",
    "ImmagineId": 62,
    "Stelle": 5.0,
    "Data": "2024-03-24T00:00:00+01:00",
    "Commento": "vdscdscs",
    "Visibile": false,
    "Moderato": true
  },
  {
    "Id": 30,
    "Nome": "s.ussi@yahoo.it",
    "ImmagineId": 3,
    "Stelle": 4.0,
    "Data": "2024-04-09T00:00:00+02:00",
    "Commento": null,
    "Visibile": true,
    "Moderato": false
  },
  {
    "Id": 31,
    "Nome": "s.ussi@yahoo.it",
    "ImmagineId": 3,
    "Stelle": 4.0,
    "Data": "2024-04-09T00:00:00+02:00",
    "Commento": null,
    "Visibile": true,
    "Moderato": false
  },
  {
    "Id": 32,
    "Nome": "s.ussi@yahoo.it",
    "ImmagineId": 3,
    "Stelle": 4.0,
    "Data": "2024-04-09T00:00:00+02:00",
    "Commento": null,
    "Visibile": true,
    "Moderato": false
  },
  {
    "Id": 33,
    "Nome": "s.ussi@yahoo.it",
    "ImmagineId": 3,
    "Stelle": 4.0,
    "Data": "2024-04-09T00:00:00+02:00",
    "Commento": null,
    "Visibile": true,
    "Moderato": false
  },
  {
    "Id": 34,
    "Nome": "s.ussi@yahoo.it",
    "ImmagineId": 2,
    "Stelle": 4.0,
    "Data": "2024-04-09T00:00:00+02:00",
    "Commento": null,
    "Visibile": true,
    "Moderato": false
  },
  {
    "Id": 35,
    "Nome": "s.ussi@yahoo.it",
    "ImmagineId": 4,
    "Stelle": 5.0,
    "Data": "2024-04-09T00:00:00+02:00",
    "Commento": "bellla!!!",
    "Visibile": true,
    "Moderato": false
  },
  {
    "Id": 36,
    "Nome": "s.ussi@yahoo.it",
    "ImmagineId": 52,
    "Stelle": 5.0,
    "Data": "2024-04-09T00:00:00+02:00",
    "Commento": "che cariniiii!!!",
    "Visibile": true,
    "Moderato": false
  },
  {
    "Id": 37,
    "Nome": "s.ussi@yahoo.it",
    "ImmagineId": 22,
    "Stelle": 5.0,
    "Data": "2024-04-09T00:00:00+02:00",
    "Commento": "cibooooooooooooo",
    "Visibile": true,
    "Moderato": false
  },
  {
    "Id": 38,
    "Nome": "s.ussi@yahoo.it",
    "ImmagineId": 62,
    "Stelle": 5.0,
    "Data": "2024-04-09T00:00:00+02:00",
    "Commento": null,
    "Visibile": true,
    "Moderato": false
  },
  {
    "Id": 39,
    "Nome": "s.ussi@yahoo.it",
    "ImmagineId": 25,
    "Stelle": 4.0,
    "Data": "2024-04-09T00:00:00+02:00",
    "Commento": "kjkh",
    "Visibile": true,
    "Moderato": false
  },
  {
    "Id": 40,
    "Nome": "s.ussi@yahoo.it",
    "ImmagineId": 55,
    "Stelle": 4.0,
    "Data": "2024-04-09T00:00:00+02:00",
    "Commento": "ffdgfdgdf",
    "Visibile": true,
    "Moderato": false
  },
  {
    "Id": 41,
    "Nome": "s.ussi@yahoo.it",
    "ImmagineId": 9,
    "Stelle": 4.0,
    "Data": "2024-04-09T00:00:00+02:00",
    "Commento": null,
    "Visibile": true,
    "Moderato": false
  },
  {
    "Id": 42,
    "Nome": "s.ussi@yahoo.it",
    "ImmagineId": 82,
    "Stelle": 5.0,
    "Data": "2024-04-09T00:00:00+02:00",
    "Commento": null,
    "Visibile": true,
    "Moderato": false
  },
  {
    "Id": 43,
    "Nome": "s.ussi@yahoo.it",
    "ImmagineId": 83,
    "Stelle": 4.0,
    "Data": "2024-04-09T00:00:00+02:00",
    "Commento": "sdsd",
    "Visibile": true,
    "Moderato": false
  },
  {
    "Id": 44,
    "Nome": "s.ussi@yahoo.it",
    "ImmagineId": 33,
    "Stelle": 5.0,
    "Data": "2024-04-09T00:00:00+02:00",
    "Commento": "sfssa",
    "Visibile": true,
    "Moderato": false
  },
  {
    "Id": 45,
    "Nome": "s.ussi@yahoo.it",
    "ImmagineId": 18,
    "Stelle": 4.0,
    "Data": "2024-04-09T00:00:00+02:00",
    "Commento": null,
    "Visibile": true,
    "Moderato": false
  },
  {
    "Id": 46,
    "Nome": "s.ussi@yahoo.it",
    "ImmagineId": 19,
    "Stelle": 5.0,
    "Data": "2024-04-09T00:00:00+02:00",
    "Commento": null,
    "Visibile": true,
    "Moderato": false
  },
  {
    "Id": 47,
    "Nome": "s.ussi@yahoo.it",
    "ImmagineId": 81,
    "Stelle": 5.0,
    "Data": "2024-04-09T00:00:00+02:00",
    "Commento": null,
    "Visibile": true,
    "Moderato": false
  },
  {
    "Id": 48,
    "Nome": "s.ussi@yahoo.it",
    "ImmagineId": 5,
    "Stelle": 4.0,
    "Data": "2024-04-09T00:00:00+02:00",
    "Commento": null,
    "Visibile": true,
    "Moderato": false
  },
  {
    "Id": 49,
    "Nome": "s.ussi@yahoo.it",
    "ImmagineId": 13,
    "Stelle": 4.0,
    "Data": "2024-04-09T00:00:00+02:00",
    "Commento": null,
    "Visibile": true,
    "Moderato": false
  },
  {
    "Id": 50,
    "Nome": "s.ussi@yahoo.it",
    "ImmagineId": 8,
    "Stelle": 3.0,
    "Data": "2024-04-09T00:00:00+02:00",
    "Commento": null,
    "Visibile": true,
    "Moderato": false
  },
  {
    "Id": 51,
    "Nome": "s.ussi@yahoo.it",
    "ImmagineId": 49,
    "Stelle": 2.0,
    "Data": "2024-04-09T00:00:00+02:00",
    "Commento": null,
    "Visibile": true,
    "Moderato": false
  },
  {
    "Id": 52,
    "Nome": "s.ussi@yahoo.it",
    "ImmagineId": 11,
    "Stelle": 3.0,
    "Data": "2024-04-09T00:00:00+02:00",
    "Commento": null,
    "Visibile": true,
    "Moderato": false
  },
  {
    "Id": 53,
    "Nome": "s.ussi@yahoo.it",
    "ImmagineId": 47,
    "Stelle": 3.0,
    "Data": "2024-04-09T00:00:00+02:00",
    "Commento": null,
    "Visibile": true,
    "Moderato": false
  },
  {
    "Id": 54,
    "Nome": "s.ussi@yahoo.it",
    "ImmagineId": 45,
    "Stelle": 5.0,
    "Data": "2024-04-09T00:00:00+02:00",
    "Commento": "rrtreter",
    "Visibile": true,
    "Moderato": false
  },
  {
    "Id": 55,
    "Nome": "s.ussi@yahoo.it",
    "ImmagineId": 85,
    "Stelle": 5.0,
    "Data": "2024-04-09T00:00:00+02:00",
    "Commento": "Pongusooooo!!!!",
    "Visibile": true,
    "Moderato": false
  },
  {
    "Id": 56,
    "Nome": "s.ussi@yahoo.it",
    "ImmagineId": 24,
    "Stelle": 5.0,
    "Data": "2024-04-09T00:00:00+02:00",
    "Commento": null,
    "Visibile": true,
    "Moderato": false
  },
  {
    "Id": 57,
    "Nome": "s.ussi@yahoo.it",
    "ImmagineId": 90,
    "Stelle": 4.0,
    "Data": "2024-04-09T00:00:00+02:00",
    "Commento": null,
    "Visibile": true,
    "Moderato": false
  },
  {
    "Id": 58,
    "Nome": "s.ussi@yahoo.it",
    "ImmagineId": 91,
    "Stelle": 5.0,
    "Data": "2024-04-09T00:00:00+02:00",
    "Commento": null,
    "Visibile": true,
    "Moderato": false
  },
  {
    "Id": 59,
    "Nome": "s.ussi@yahoo.it",
    "ImmagineId": 72,
    "Stelle": 5.0,
    "Data": "2024-04-10T00:00:00+02:00",
    "Commento": "sssasaas",
    "Visibile": true,
    "Moderato": false
  },
  {
    "Id": 60,
    "Nome": "giada@gmail.com",
    "ImmagineId": 3,
    "Stelle": 4.0,
    "Data": "2024-04-11T00:00:00+02:00",
    "Commento": "Insomma",
    "Visibile": true,
    "Moderato": false
  }
]